myapp/__init__.py
myapp/admin.py
myapp/apps.py
myapp/models.py
myapp/tests.py
myapp/urls.py
myapp/views.py
testModule000101-1.1.dist-info/METADATA
testModule000101-1.1.dist-info/WHEEL
testModule000101-1.1.dist-info/top_level.txt
testModule000101-1.1.dist-info/RECORD
