Metadata-Version: 2.1
Name: testModule000101
Version: 1.1
Summary: testModule00010
Author: Farah Ben Mohamed
Author-email: farahbenmohamed.carnelian@gmail.com
Requires-Dist: asgiref ==3.7.2
Requires-Dist: Django ==3.2.12
Requires-Dist: djangorestframework ==3.14.0
Requires-Dist: python-decouple ==3.4
Requires-Dist: pytz ==2023.3.post1
Requires-Dist: sqlparse ==0.4.4
Requires-Dist: typing-extensions ==4.8.0
